chocochip/__init__.py
chocochip/chocochip.py
chocochip-0.0.1.dist-info/LICENSE
chocochip-0.0.1.dist-info/METADATA
chocochip-0.0.1.dist-info/WHEEL
chocochip-0.0.1.dist-info/top_level.txt
chocochip-0.0.1.dist-info/RECORD
