Metadata-Version: 2.1
Name: chocochip
Version: 0.0.1
Summary: A package to provide you Chocochip cookies
Home-page: https://github.com/VigneshBaskar/chocochip
Author: Vignesh Baskaran
Author-email: vignesh.sbaskaran@gmail.com
License: UNKNOWN
Platform: UNKNOWN
Classifier: Programming Language :: Python :: 3.7
Classifier: License :: OSI Approved :: GNU General Public License v3 (GPLv3)
